README.md
setup.py
ingeniumpy/__init__.py
ingeniumpy/api.py
ingeniumpy/connection.py
ingeniumpy/connection_direct.py
ingeniumpy/objects.py
ingeniumpy.egg-info/PKG-INFO
ingeniumpy.egg-info/SOURCES.txt
ingeniumpy.egg-info/dependency_links.txt
ingeniumpy.egg-info/requires.txt
ingeniumpy.egg-info/top_level.txt
ingeniumpy/bin/proxy-arm
ingeniumpy/bin/proxy-arm64
ingeniumpy/bin/proxy-x64