Metadata-Version: 2.1
Name: ingeniumpy
Version: 0.9.6
Summary: Ingenium API
Home-page: https://pypi.org/project/ingeniumpy
Author: Daniel Garcia
Author-email: dgarcia@ingeniumsl.com
License: UNKNOWN
Platform: UNKNOWN
Classifier: Programming Language :: Python :: 3
Classifier: License :: Other/Proprietary License
Classifier: Operating System :: POSIX :: Linux
Classifier: Topic :: Home Automation
Requires-Python: >=3.7
